<?xml version="1.0" encoding="UTF-8" standalone="no"?><messages><message id="1"><author>anonymous</author><text>1</text><date>28-44-2015 13:44 </date></message><message id="2"><author/><text/><date>28-44-2015 13:44 </date></message><message id="3"><author/><text/><date>28-44-2015 13:44 </date></message><message id="4"><author/><text/><date>28-44-2015 13:44 </date></message><message id="5"><author/><text/><date>28-44-2015 13:44 </date></message><message id="6"><author/><text/><date>28-44-2015 13:44 </date></message><message id="7"><author>anonymous</author><text>27</text><date>28-44-2015 13:44 </date></message><message id="8"><author>anonymous</author><text>8</text><date>28-44-2015 13:44 </date></message><message id="9"><author/><text/><date>28-44-2015 13:44 </date></message><message id="10"><author>anonymous</author><text>normal</text><date>28-44-2015 13:44 </date></message><message id="11"><author>anonymous</author><text>klklklk</text><date>28-45-2015 13:45 </date></message></messages>